{
  "schemaVersion": 1,
  "description": "Abstract taxonomy for the Moss concept. This is a draft concept-layer grouping, not yet part of the generated scheme registry.",
  "families": {
    "environment": [
      "carbon",
      "chalk",
      "shell"
    ],
    "signalHot": [
      "spark",
      "amber"
    ],
    "signalCool": [
      "voltage"
    ],
    "signalBright": [
      "citron"
    ],
    "quietSupport": [
      "jade",
      "slate"
    ]
  },
  "roles": {
    "primarySignal": [
      "keyword",
      "function",
      "type"
    ],
    "rhythmicSupport": [
      "string",
      "number",
      "property",
      "method"
    ],
    "pageStability": [
      "comment",
      "operator",
      "variable",
      "parameter"
    ]
  },
  "surfaces": {
    "primary": [
      "canvas",
      "ink",
      "panel"
    ],
    "support": [
      "sidebar",
      "gutter",
      "border"
    ]
  },
  "interactions": {
    "persistent": [
      "cursor",
      "status",
      "tabEmphasis"
    ],
    "contextual": [
      "selection",
      "focusRing",
      "lineEmphasis",
      "listHover"
    ]
  },
  "variants": {
    "core": [
      "dark",
      "light"
    ],
    "soft": [
      "darkSoft",
      "lightSoft"
    ]
  }
}
